noqlite/__init__.py
noqlite/noqlite.py
noqlite-0.1.0.dist-info/DESCRIPTION.rst
noqlite-0.1.0.dist-info/METADATA
noqlite-0.1.0.dist-info/RECORD
noqlite-0.1.0.dist-info/WHEEL
noqlite-0.1.0.dist-info/metadata.json
noqlite-0.1.0.dist-info/top_level.txt
