Metadata-Version: 2.0
Name: noqlite
Version: 0.1.0
Summary: simple nosql over sqlite
Home-page: https://github.com/gowhari/noqlite
Author: Iman Gowhari
Author-email: gowhari@gmail.com
License: MIT
Platform: UNKNOWN
